odoo/addons/base_user_acl/LICENSE
odoo/addons/base_user_acl/README.rst
odoo/addons/base_user_acl/__init__.py
odoo/addons/base_user_acl/__manifest__.py
odoo/addons/base_user_acl/i18n/de_CH.po
odoo/addons/base_user_acl/images/screen.png
odoo/addons/base_user_acl/security/security.xml
odoo/addons/base_user_acl/static/description/icon.png
odoo/addons/base_user_acl/static/description/index.html
odoo_addon_base_user_acl-16.0.1.0.0.dist-info/METADATA
odoo_addon_base_user_acl-16.0.1.0.0.dist-info/WHEEL
odoo_addon_base_user_acl-16.0.1.0.0.dist-info/top_level.txt
odoo_addon_base_user_acl-16.0.1.0.0.dist-info/RECORD
